nkosi/__init__.py
nkosi/cli.py
nkosi/communication.py
nkosi/discovery.py
nkosi/scanner.py
nkosi/visualizer.py
nkosi-3.4.dist-info/METADATA
nkosi-3.4.dist-info/WHEEL
nkosi-3.4.dist-info/entry_points.txt
nkosi-3.4.dist-info/top_level.txt
nkosi-3.4.dist-info/RECORD
