Metadata-Version: 2.1
Name: nkosi
Version: 3.4
Summary: A network tool for device discovery and communication
Author-email: Nandhan K <developer.nandhank@gmail.com>
License: MIT
Project-URL: Homepage, https://github.com/Nandhan-KA/nkosi
Project-URL: Documentation, https://github.com/Nandhan-KA/nkosi#readme
Project-URL: Repository, https://github.com/Nandhan-KA/nkosi
Project-URL: BugTracker, https://github.com/Nandhan-KA/nkosi/issues
Keywords: Network Discovery,OSI Model Visualizer,Network Tools,TCP/UDP Communication
Classifier: Programming Language :: Python :: 3
Classifier: License :: OSI Approved :: MIT License
Classifier: Operating System :: Microsoft :: Windows
Classifier: Operating System :: POSIX :: Linux
Classifier: Environment :: Win32 (MS Windows)
Classifier: Programming Language :: Python :: 3.8
Classifier: Programming Language :: Python :: 3.9
Classifier: Programming Language :: Python :: 3.10
Classifier: Programming Language :: Python :: 3.11
Classifier: Programming Language :: Python :: 3.12
Classifier: Programming Language :: Python :: 3.13
Requires-Python: >=3.8
Requires-Dist: rich>=13.0.0
Requires-Dist: ipaddress>=1.0.0
Requires-Dist: netifaces>=0.11.0
Requires-Dist: python-nmap>=0.7.1
Requires-Dist: scapy>=2.5.0
Requires-Dist: psutil>=5.9.0
Requires-Dist: requests>=2.31.0
Provides-Extra: dev
Requires-Dist: pytest>=6.0; extra == "dev"
Requires-Dist: black>=21.5b2; extra == "dev"
Requires-Dist: isort>=5.8.0; extra == "dev"
Requires-Dist: mypy>=0.812; extra == "dev"
Requires-Dist: pylint>=2.8.2; extra == "dev"
Provides-Extra: linux
Requires-Dist: arp-scan; extra == "linux"
Requires-Dist: tcpdump; extra == "linux"
Requires-Dist: nmap; extra == "linux"
